MANIFEST.in
README.md
requirements.txt
setup.py
markdown_predictions/__init__.py
markdown_predictions/clean_data.py
markdown_predictions/parse_data.py
markdown_predictions/selection.py
markdown_predictions/trainer.py
markdown_predictions/utils.py
markdown_predictions.egg-info/PKG-INFO
markdown_predictions.egg-info/SOURCES.txt
markdown_predictions.egg-info/dependency_links.txt
markdown_predictions.egg-info/not-zip-safe
markdown_predictions.egg-info/requires.txt
markdown_predictions.egg-info/top_level.txt
scripts/markdown_predictions-run
tests/__init__.py
tests/test_parse_data.py