Metadata-Version: 1.0
Name: markdown-predictions
Version: 1.17
Summary: Predicting two-weeks of unit sales for different possible product markdowns
Home-page: UNKNOWN
Author: UNKNOWN
Author-email: UNKNOWN
License: UNKNOWN
Platform: UNKNOWN
